vitextaug/__init__.py
vitextaug/augmentor.py
vitextaug-0.0.9.dist-info/LICENSE.txt
vitextaug-0.0.9.dist-info/METADATA
vitextaug-0.0.9.dist-info/WHEEL
vitextaug-0.0.9.dist-info/top_level.txt
vitextaug-0.0.9.dist-info/RECORD
