Metadata-Version: 2.1
Name: vitextaug
Version: 0.0.9
Summary: Text data augmentation for Vietnamese
Home-page: https://github.com/longcld/vitextaug.git
Author: LongLich
Author-email: long.itptit@gmail.com
Classifier: Programming Language :: Python :: 3
Classifier: License :: OSI Approved :: MIT License
Classifier: Operating System :: OS Independent
Requires-Python: >=3.6
License-File: LICENSE.txt
Requires-Dist: vncorenlp
